glucograph/__init__.py
glucograph/analyzer.py
glucograph/cli.py
glucograph/diagram.py
glucograph-1.0.5.dist-info/METADATA
glucograph-1.0.5.dist-info/WHEEL
glucograph-1.0.5.dist-info/entry_points.txt
glucograph-1.0.5.dist-info/licenses/LICENSE
glucograph-1.0.5.dist-info/RECORD
