Metadata-Version: 2.1
Name: glucograph
Version: 1.0.5
Summary: This project contains an application, which plots data exported from CGM (Continuous Glucode Monitoring) system. Currently only data exported from xDrip (https://github.com/NightscoutFoundation/xDrip) is recognized by this program. THIS APPLICATION SHOULD NOT BE USED TO MAKE MEDICAL DECISIONS.
Project-URL: Homepage, https://gitlab.com/markok314/glucograph
Project-URL: Bug Tracker, https://gitlab.com/markok314/glucograph/-/issues
Author: Marko K
License: GPL v3
License-File: LICENSE
Keywords: glucose,xDrip
Classifier: License :: OSI Approved :: GNU Lesser General Public License v3 (LGPLv3)
Classifier: Operating System :: OS Independent
Classifier: Programming Language :: Python :: 3
Requires-Python: >=3.8
Requires-Dist: matplotlib>=3.1.0
